README.md
setup.py
ads_bidding_utils.egg-info/PKG-INFO
ads_bidding_utils.egg-info/SOURCES.txt
ads_bidding_utils.egg-info/dependency_links.txt
ads_bidding_utils.egg-info/requires.txt
ads_bidding_utils.egg-info/top_level.txt
minio_utils/__init__.py
minio_utils/operations.py