Metadata-Version: 2.1
Name: ads-bidding-utils
Version: 0.3.14
Summary: Python package for ads bidding utils
Home-page: https://github.com/sahelyiyi/ads-bidding-utils
Author: Yasmin SarcheshmehPour
Author-email: sarcheshmehpours@gmail.com
Requires-Python: >=3.8
